forefront_cli/__init__.py
forefront_cli/api.py
forefront_cli/common.py
forefront_cli/config/__init__.py
forefront_cli/config/main.py
forefront_cli/deploy/__init__.py
forefront_cli/deploy/main.py
forefront_cli/init/__init__.py
forefront_cli/init/main.py
forefront_cli/logout/__init__.py
forefront_cli/logout/main.py
forefront_cli/main.py
forefront_cli/projects/__init__.py
forefront_cli/projects/main.py
forefront_cli/versions/__init__.py
forefront_cli/versions/main.py
forefront_cli-0.1.2.dist-info/entry_points.txt
forefront_cli-0.1.2.dist-info/WHEEL
forefront_cli-0.1.2.dist-info/METADATA
forefront_cli-0.1.2.dist-info/RECORD
