Metadata-Version: 2.1
Name: forefront-cli
Version: 0.1.2
Summary: 
Author: Mike
Author-email: michaelrturck@gmail.com
Requires-Python: >=3.9,<4.0
Classifier: Programming Language :: Python :: 3
Classifier: Programming Language :: Python :: 3.9
Requires-Dist: PyInquirer (>=1.0.3,<2.0.0)
Requires-Dist: click (>=8.0.1,<9.0.0)
Requires-Dist: halo (>=0.0.31,<0.0.32)
Requires-Dist: prettytable (>=2.1.0,<3.0.0)
Requires-Dist: requests (>=2.25.1,<3.0.0)
